LICENSE.txt
MANIFEST.in
README.md
pypinex_info.json
setup.py
pypinex_less/LessC.py
pypinex_less/__init__.py
pypinex_less.egg-info/PKG-INFO
pypinex_less.egg-info/SOURCES.txt
pypinex_less.egg-info/dependency_links.txt
pypinex_less.egg-info/not-zip-safe
pypinex_less.egg-info/requires.txt
pypinex_less.egg-info/top_level.txt