Metadata-Version: 2.1
Name: pypinex-less
Version: 0.2021.3.20
Summary: Support for 'less' files in PyPine.
Home-page: UNKNOWN
Author: Jürgen Knauth
Author-email: pubsrc@binary-overflow.de
License: Apache2
Keywords: pypine,pypinex,less
Platform: UNKNOWN
Classifier: Development Status :: 5 - Production/Stable
Classifier: License :: OSI Approved :: Apache Software License
Classifier: Programming Language :: Python :: 3
